{
  "currentClaim": "Threadsmith v0.2.0 Role-specific Packets v1 is accepted locally: each role receives a focused packet derived from the main Context Packet, with fs persistence under role-packets.",
  "doneWhenChecklist": [
    {
      "id": "role-packet-schema",
      "label": "RoleContextPacket schema 已定义并从 domain 导出",
      "status": "pass"
    },
    {
      "id": "role-packet-builder",
      "label": "runtime 可以从主 Context Packet 派生六类 role packet",
      "status": "pass"
    },
    {
      "id": "role-packet-focus",
      "label": "planner / executor / reviewer / verifier / closeout / hygiene 各自聚焦不同 payload",
      "status": "pass"
    },
    {
      "id": "role-packet-persistence",
      "label": "fs-bridge 可以写入和读取 .threadsmith/context/role-packets/<role>.json",
      "status": "pass"
    },
    {
      "id": "targeted-tests",
      "label": "domain/runtime/fs-bridge targeted tests 通过",
      "status": "pass"
    }
  ],
  "implementationStatus": "ready-for-review",
  "reviewStatus": "ready-for-verification",
  "verificationStatus": "passed",
  "closeoutStatus": "done",
  "knownGaps": [
    "This slice does not change Threadsmith.skill behavior yet.",
    "This slice does not render role packets in the Control Deck UI.",
    "Role packet payloads should stay deterministic and derived from the main Context Packet."
  ],
  "finalState": "accepted"
}
