{
  "phaseName": "Proposal Review / Adoption v1",
  "phaseGoal": "定义 writeback proposal 的审查/采纳计划，让 Threadsmith 能明确拒绝、要求恢复或生成可人工采纳的计划，同时不自动修改 committed truth。",
  "deliverable": "proposal review domain contract、fs-bridge review artifact helper、action/runtime contract 文档与对应测试。",
  "inScope": [
    "定义 writeback proposal review decision schema",
    "支持 accept-plan / reject / needs-recovery 三种审查结果",
    "accept-plan 只能生成待人工应用的 adoption plan，不直接写 committed truth",
    "新增 fs-bridge helper 写入 .threadsmith/proposal-reviews/<proposal-id>.json",
    "增加 domain / fs-bridge 测试覆盖 review artifact 与 no-auto-adoption 边界"
  ],
  "outOfScope": [
    "自动采纳 proposal 并直接写 committed truth",
    "实现 proposal review UI",
    "让外部 agent 直接写 committed truth",
    "改动前端 UI",
    "修改或安装全局 ~/.codex/skills/threadsmith/SKILL.md",
    "发布 release"
  ],
  "stopCondition": "proposal review 能产出可审计的 accept-plan / reject / needs-recovery artifact，且测试证明 accept-plan 不会自动写 committed truth。",
  "verificationForThisPhase": [
    "npm run verify:project-truth",
    "npm run test --workspace @threadsmith/domain",
    "npm run test --workspace @threadsmith/fs-bridge",
    "npm run verify:skill-contract",
    "git diff --check",
    "jq empty .threadsmith/*.json"
  ],
  "activeOwners": [
    "planner",
    "executor",
    "reviewer",
    "verifier",
    "closeout"
  ],
  "blockedBy": []
}
