{
  "phaseName": "Bridge Refresh Command v1",
  "phaseGoal": "为 Cross-Agent State Bridge v1 增加一条 operator 命令，把 truth 校验、handoff 刷新和 adapter 刷新合成一个可重复入口。",
  "deliverable": "threadsmith:bridge-refresh command、smoke coverage、operator docs update、truth closeout。",
  "inScope": [
    "新增 npm run threadsmith:bridge-refresh -- .",
    "命令先加载并校验 committed truth，再刷新 fixed handoff 和 provider adapter prompts",
    "输出 project root、phase、final state、handoff path、adapter paths 和 freshness anchor",
    "新增 isolated smoke，证明命令会写出 handoff/adapters",
    "更新 Cross-Agent State Bridge v1 文档和 operator guide"
  ],
  "outOfScope": [
    "前端维护或重构",
    "multi-provider 自动执行",
    "外部 agent 直接写 committed truth",
    "proposal review UI",
    "发布 release",
    "修改或安装全局 ~/.codex/skills/threadsmith/SKILL.md",
    "External-agent fixture pack"
  ],
  "stopCondition": "操作者能用一条 bridge-refresh 命令刷新跨 agent 交接面，而不需要手动记住 verify + handoff + adapters 三步。",
  "verificationForThisPhase": [
    "npm run smoke:bridge-refresh",
    "npm run threadsmith:bridge-refresh -- .",
    "npm run threadsmith:handoff -- .",
    "npm run threadsmith:adapters -- .",
    "npm run verify:project-truth",
    "npm run verify:skill-contract",
    "git diff --check",
    "jq empty .threadsmith/*.json"
  ],
  "activeOwners": [
    "planner",
    "executor",
    "reviewer",
    "verifier",
    "closeout"
  ],
  "blockedBy": []
}
